{
  "_id": "JCKoJrZsZNjJdMq0",
  "name": "Biker Punk",
  "type": "npc",
  "img": "icons/svg/mystery-man.svg",
  "system": {
    "abilities": {
      "str": {
        "value": 13,
        "proficient": 0,
        "bonuses": {
          "check": "",
          "save": ""
        }
      },
      "dex": {
        "value": 15,
        "proficient": 0,
        "bonuses": {
          "check": "",
          "save": ""
        }
      },
      "con": {
        "value": 13,
        "proficient": 0,
        "bonuses": {
          "check": "",
          "save": ""
        }
      },
      "int": {
        "value": 10,
        "proficient": 0,
        "bonuses": {
          "check": "",
          "save": ""
        }
      },
      "wis": {
        "value": 11,
        "proficient": 0,
        "bonuses": {
          "check": "",
          "save": ""
        }
      },
      "cha": {
        "value": 11,
        "proficient": 0,
        "bonuses": {
          "check": "",
          "save": ""
        }
      }
    },
    "attributes": {
      "ac": {
        "flat": 13,
        "calc": "flat",
        "formula": ""
      },
      "hp": {
        "value": 38,
        "max": 38,
        "temp": 0,
        "tempmax": 0,
        "formula": "7d8 + 7"
      },
      "init": {
        "ability": "",
        "bonus": ""
      },
      "movement": {
        "burrow": 0,
        "climb": 0,
        "fly": 0,
        "swim": 0,
        "walk": 30,
        "units": "ft",
        "hover": false
      },
      "senses": {
        "darkvision": 0,
        "blindsight": 0,
        "tremorsense": 0,
        "truesight": 0,
        "units": "ft",
        "special": ""
      },
      "spellcasting": "",
      "death": {
        "success": 0,
        "failure": 0
      },
      "exhaustion": 0,
      "inspiration": false
    },
    "details": {
      "biography": {
        "value": "",
        "public": ""
      },
      "alignment": "any non-lawful alignment",
      "race": "",
      "type": {
        "value": "humanoid",
        "subtype": "any race",
        "swarm": "",
        "custom": ""
      },
      "environment": "",
      "cr": 0.5,
      "spellLevel": 0,
      "source": {
        "custom": "Technomancer's Textbook"
      }
    },
    "traits": {
      "size": "med",
      "di": {
        "value": [],
        "bypasses": [],
        "custom": ""
      },
      "dr": {
        "value": [],
        "bypasses": [],
        "custom": ""
      },
      "dv": {
        "value": [],
        "bypasses": [],
        "custom": ""
      },
      "ci": {
        "value": [],
        "custom": ""
      },
      "languages": {
        "value": [],
        "custom": "any one language (usually Common)"
      }
    },
    "skills": {
      "acr": {
        "value": 1,
        "ability": "dex",
        "bonuses": {
          "check": "",
          "passive": ""
        }
      },
      "ani": {
        "value": 0,
        "ability": "wis",
        "bonuses": {
          "check": "",
          "passive": ""
        }
      },
      "arc": {
        "value": 0,
        "ability": "int",
        "bonuses": {
          "check": "",
          "passive": ""
        }
      },
      "ath": {
        "value": 0,
        "ability": "str",
        "bonuses": {
          "check": "",
          "passive": ""
        }
      },
      "dec": {
        "value": 0,
        "ability": "cha",
        "bonuses": {
          "check": "",
          "passive": ""
        }
      },
      "his": {
        "value": 0,
        "ability": "int",
        "bonuses": {
          "check": "",
          "passive": ""
        }
      },
      "ins": {
        "value": 0,
        "ability": "wis",
        "bonuses": {
          "check": "",
          "passive": ""
        }
      },
      "itm": {
        "value": 1,
        "ability": "cha",
        "bonuses": {
          "check": "",
          "passive": ""
        }
      },
      "inv": {
        "value": 0,
        "ability": "int",
        "bonuses": {
          "check": "",
          "passive": ""
        }
      },
      "med": {
        "value": 0,
        "ability": "wis",
        "bonuses": {
          "check": "",
          "passive": ""
        }
      },
      "nat": {
        "value": 0,
        "ability": "int",
        "bonuses": {
          "check": "",
          "passive": ""
        }
      },
      "prc": {
        "value": 0,
        "ability": "wis",
        "bonuses": {
          "check": "",
          "passive": ""
        }
      },
      "prf": {
        "value": 0,
        "ability": "cha",
        "bonuses": {
          "check": "",
          "passive": ""
        }
      },
      "per": {
        "value": 0,
        "ability": "cha",
        "bonuses": {
          "check": "",
          "passive": ""
        }
      },
      "rel": {
        "value": 0,
        "ability": "int",
        "bonuses": {
          "check": "",
          "passive": ""
        }
      },
      "slt": {
        "value": 0,
        "ability": "dex",
        "bonuses": {
          "check": "",
          "passive": ""
        }
      },
      "ste": {
        "value": 0,
        "ability": "dex",
        "bonuses": {
          "check": "",
          "passive": ""
        }
      },
      "sur": {
        "value": 0,
        "ability": "wis",
        "bonuses": {
          "check": "",
          "passive": ""
        }
      }
    },
    "resources": {
      "legact": {
        "value": 0,
        "max": 0
      },
      "legres": {
        "value": 0,
        "max": 0
      },
      "lair": {
        "value": false,
        "initiative": 20
      }
    },
    "currency": {
      "pp": 0,
      "gp": 0,
      "ep": 0,
      "sp": 0,
      "cp": 0
    },
    "bonuses": {
      "mwak": {
        "attack": "",
        "damage": ""
      },
      "rwak": {
        "attack": "",
        "damage": ""
      },
      "msak": {
        "attack": "",
        "damage": ""
      },
      "rsak": {
        "attack": "",
        "damage": ""
      },
      "abilities": {
        "check": "",
        "save": "",
        "skill": ""
      },
      "spell": {
        "dc": ""
      }
    }
  },
  "items": [
    {
      "_id": "A3PuNGhgObuA0USe",
      "name": "Multiattack",
      "type": "feat",
      "img": "icons/skills/melee/blade-tips-triple-steel.webp",
      "system": {
        "description": {
          "value": "The punk makes two attacks with its heavy chain or machine pistol, or one bola attack.",
          "chat": ""
        },
        "source": {
          "custom": ""
        },
        "activation": {
          "type": "action",
          "cost": 1,
          "condition": ""
        },
        "duration": {
          "value": null,
          "units": ""
        },
        "target": {
          "value": null,
          "width": null,
          "units": "",
          "type": ""
        },
        "range": {
          "value": null,
          "long": null,
          "units": ""
        },
        "uses": {
          "value": null,
          "max": "",
          "per": null,
          "recovery": ""
        },
        "consume": {
          "type": "",
          "target": null,
          "amount": null
        },
        "recharge": {
          "value": null,
          "charged": false
        }
      },
      "effects": [],
      "flags": {},
      "_key": "!actors.items!JCKoJrZsZNjJdMq0.A3PuNGhgObuA0USe"
    },
    {
      "_id": "ORnIOPC37oG0Tr3k",
      "name": "Heavy Chain",
      "type": "weapon",
      "img": "icons/tools/fasteners/chain-steel-grey.webp",
      "system": {
        "description": {
          "value": "Melee Weapon Attack: +4 to hit, reach 10 ft., one target. Hit: 5 (1d4 + 3) bludgeoning damage.",
          "chat": ""
        },
        "source": {
          "custom": ""
        },
        "quantity": 1,
        "weight": {
          "value": 0,
          "units": "lb"
        },
        "price": {
          "value": 0,
          "denomination": "gp"
        },
        "attunement": 0,
        "equipped": true,
        "rarity": "",
        "identified": true,
        "activation": {
          "type": "action",
          "cost": 1,
          "condition": ""
        },
        "duration": {
          "value": null,
          "units": ""
        },
        "target": {
          "value": null,
          "width": null,
          "units": "",
          "type": "creature"
        },
        "range": {
          "value": 10,
          "long": null,
          "units": "ft"
        },
        "uses": {
          "value": null,
          "max": "",
          "per": null,
          "recovery": ""
        },
        "consume": {
          "type": "",
          "target": null,
          "amount": null
        },
        "ability": "dex",
        "actionType": "mwak",
        "attackBonus": "",
        "chatFlavor": "",
        "critical": {
          "threshold": null,
          "damage": ""
        },
        "damage": {
          "parts": [
            [
              "1d4 + 3",
              "bludgeoning"
            ]
          ],
          "versatile": ""
        },
        "formula": "",
        "save": {
          "ability": "",
          "dc": null,
          "scaling": "spell"
        },
        "armor": {
          "value": 10
        },
        "hp": {
          "value": 0,
          "max": 0,
          "dt": null,
          "conditions": ""
        },
        "weaponType": "simpleM",
        "baseItem": "",
        "properties": {},
        "proficient": null
      },
      "effects": [],
      "flags": {},
      "_key": "!actors.items!JCKoJrZsZNjJdMq0.ORnIOPC37oG0Tr3k"
    },
    {
      "_id": "UttNnExi0gDawG0j",
      "name": "Machine Pistol",
      "type": "weapon",
      "img": "modules/cyberpunk-5e/assets/weapon_icons/firearm_icons/machine_pistol.png",
      "system": {
        "description": {
          "value": "Ranged Weapon Attack: +4 to hit, range 30/90 ft., one target. Hit: 5 (2d4) piercing damage. This weapon has the automatic, foregrip, light, reload (10) properties.",
          "chat": ""
        },
        "source": {
          "custom": ""
        },
        "quantity": 1,
        "weight": {
          "value": 0,
          "units": "lb"
        },
        "price": {
          "value": 0,
          "denomination": "gp"
        },
        "attunement": 0,
        "equipped": true,
        "rarity": "",
        "identified": true,
        "activation": {
          "type": "action",
          "cost": 1,
          "condition": ""
        },
        "duration": {
          "value": null,
          "units": ""
        },
        "target": {
          "value": null,
          "width": null,
          "units": "",
          "type": "creature"
        },
        "range": {
          "value": 50,
          "long": 200,
          "units": "ft"
        },
        "uses": {
          "value": null,
          "max": "",
          "per": null,
          "recovery": ""
        },
        "consume": {
          "type": "",
          "target": null,
          "amount": null
        },
        "ability": "dex",
        "actionType": "rwak",
        "attackBonus": "",
        "chatFlavor": "",
        "critical": {
          "threshold": null,
          "damage": ""
        },
        "damage": {
          "parts": [
            [
              "2d4",
              "piercing"
            ]
          ],
          "versatile": ""
        },
        "formula": "",
        "save": {
          "ability": "",
          "dc": null,
          "scaling": "spell"
        },
        "armor": {
          "value": 10
        },
        "hp": {
          "value": 0,
          "max": 0,
          "dt": null,
          "conditions": ""
        },
        "weaponType": "simpleR",
        "baseItem": "",
        "properties": {},
        "proficient": null
      },
      "effects": [],
      "flags": {},
      "_key": "!actors.items!JCKoJrZsZNjJdMq0.UttNnExi0gDawG0j"
    },
    {
      "_id": "d9j7C7JXH0Xk4BM7",
      "name": "Bola",
      "type": "weapon",
      "img": "icons/weapons/thrown/bolas-steel.webp",
      "system": {
        "description": {
          "value": "Ranged Weapon Attack: +4 to hit, reach 40/120 ft., one Large or smaller creature. Hit: The target is restrained. A creature can use its action to make a DC 10 Strength check to free itself or another creature in a bola, ending the effect on a success. Dealing 5 slashing damage to the bola (AC 10) frees the target without harming it and destroys the bola.",
          "chat": ""
        },
        "source": {
          "custom": ""
        },
        "quantity": 1,
        "weight": {
          "value": 0,
          "units": "lb"
        },
        "price": {
          "value": 0,
          "denomination": "gp"
        },
        "attunement": 0,
        "equipped": true,
        "rarity": "",
        "identified": true,
        "activation": {
          "type": "action",
          "cost": 1,
          "condition": ""
        },
        "duration": {
          "value": null,
          "units": ""
        },
        "target": {
          "value": null,
          "width": null,
          "units": "",
          "type": "creature"
        },
        "range": {
          "value": null,
          "long": null,
          "units": "ft"
        },
        "uses": {
          "value": null,
          "max": "",
          "per": null,
          "recovery": ""
        },
        "consume": {
          "type": "",
          "target": null,
          "amount": null
        },
        "ability": "dex",
        "actionType": "rwak",
        "attackBonus": "",
        "chatFlavor": "",
        "critical": {
          "threshold": null,
          "damage": ""
        },
        "damage": {
          "parts": [],
          "versatile": ""
        },
        "formula": "",
        "save": {
          "ability": "",
          "dc": null,
          "scaling": "spell"
        },
        "armor": {
          "value": 10
        },
        "hp": {
          "value": 0,
          "max": 0,
          "dt": null,
          "conditions": ""
        },
        "weaponType": "simpleR",
        "baseItem": "",
        "properties": {},
        "proficient": null
      },
      "effects": [],
      "flags": {},
      "_key": "!actors.items!JCKoJrZsZNjJdMq0.d9j7C7JXH0Xk4BM7"
    }
  ],
  "effects": [],
  "flags": {},
  "folder": null,
  "_key": "!actors!JCKoJrZsZNjJdMq0"
}
